poseidonrna/__init__.py
poseidonrna/poseidonrna.py
poseidonrna/Structures/3D_#DNA_IRES.png
poseidonrna/Structures/3D_#DNA_IRES.svg
poseidonrna/Structures/3D_a580__full.png
poseidonrna/Structures/3D_a580__full.svg
poseidonrna/Structures/a580__full.png
poseidonrna/Structures/a580__full.svg
poseidon_rna-0.22.dist-info/METADATA
poseidon_rna-0.22.dist-info/WHEEL
poseidon_rna-0.22.dist-info/RECORD
