Metadata-Version: 2.4
Name: poseidon-rna
Version: 0.22
Summary: Plotting RNA using Kamada-Kawai Graph Plotting Algorithm
Project-URL: Homepage, https://github.com/rouskinlab/poseidon-rna
Project-URL: Bug Tracker, https://github.com/rouskinlab/poseidon-rna/issues
Author: Adam Sychla
License: GPL-3.0-only
Classifier: Operating System :: OS Independent
Classifier: Programming Language :: Python :: 3
Requires-Python: >=3.10
Requires-Dist: matplotlib>=3.8.4
Requires-Dist: networkx>=3.3
Requires-Dist: numpy>=1.26.4
Requires-Dist: pandas
Requires-Dist: progress
Requires-Dist: scipy>=1.13.0
Requires-Dist: seaborn>=0.13.2
